{
  "request_id": "1587045721,b55039bd-0e39-4ef2-9ecf-173b88c7a514",
  "time_used": 92,
  "faces": [
    {
      "face_token": "491aa95c7887efc367f2ac55f8d17317",
      "face_rectangle": {
        "top": 186,
        "left": 41,
        "width": 226,
        "height": 226
      },
      "landmark": {
        "hair1": {
          "x": 39,
          "y": 85
        },
        "hair2": {
          "x": 129,
          "y": 34
        },
        "hair3": {
          "x": 226,
          "y": 63
        },
        "11": {
          "x": 48,
          "y": 451
        },
        "12": {
          "x": 90,
          "y": 418
        },
        "13": {
          "x": 111,
          "y": 499
        },
        "14": {
          "x": 215,
          "y": 428
        },
        "15": {
          "x": 256,
          "y": 357
        },
        "16": {
          "x": 291,
          "y": 381
        },
        "1":{
          "x": 0,
          "y": 0
        },
        "2": {
          "x": 321,
          "y": 0
        },
        "3": {
          "x": 0,
          "y": 475
        },
        "4": {
          "x": 321,
          "y": 475
        },
        "5": {
          "x": 161,
          "y": 0
        },
        "6": {
          "x": 0,
          "y": 238
        },
        "7": {
          "x": 161,
          "y": 475
        },
        "8": {
          "x": 321,
          "y": 238
        },
        "contour_chin": {
          "x": 162,
          "y": 412
        },
        "contour_left1": {
          "x": 39,
          "y": 234
        },
        "contour_left2": {
          "x": 40,
          "y": 260
        },
        "contour_left3": {
          "x": 44,
          "y": 286
        },
        "contour_left4": {
          "x": 48,
          "y": 312
        },
        "contour_left5": {
          "x": 56,
          "y": 338
        },
        "contour_left6": {
          "x": 69,
          "y": 362
        },
        "contour_left7": {
          "x": 86,
          "y": 381
        },
        "contour_left8": {
          "x": 108,
          "y": 397
        },
        "contour_left9": {
          "x": 133,
          "y": 409
        },
        "contour_right1": {
          "x": 255,
          "y": 213
        },
        "contour_right2": {
          "x": 258,
          "y": 240
        },
        "contour_right3": {
          "x": 258,
          "y": 266
        },
        "contour_right4": {
          "x": 258,
          "y": 293
        },
        "contour_right5": {
          "x": 256,
          "y": 320
        },
        "contour_right6": {
          "x": 247,
          "y": 345
        },
        "contour_right7": {
          "x": 233,
          "y": 368
        },
        "contour_right8": {
          "x": 214,
          "y": 388
        },
        "contour_right9": {
          "x": 191,
          "y": 404
        },
        "left_eye_bottom": {
          "x": 100,
          "y": 227
        },
        "left_eye_center": {
          "x": 99,
          "y": 223
        },
        "left_eye_left_corner": {
          "x": 80,
          "y": 227
        },
        "left_eye_lower_left_quarter": {
          "x": 89,
          "y": 228
        },
        "left_eye_lower_right_quarter": {
          "x": 110,
          "y": 225
        },
        "left_eye_pupil": {
          "x": 99,
          "y": 221
        },
        "left_eye_right_corner": {
          "x": 119,
          "y": 222
        },
        "left_eye_top": {
          "x": 99,
          "y": 216
        },
        "left_eye_upper_left_quarter": {
          "x": 88,
          "y": 220
        },
        "left_eye_upper_right_quarter": {
          "x": 110,
          "y": 217
        },
        "left_eyebrow_left_corner": {
          "x": 58,
          "y": 223
        },
        "left_eyebrow_lower_left_quarter": {
          "x": 71,
          "y": 215
        },
        "left_eyebrow_lower_middle": {
          "x": 86,
          "y": 209
        },
        "left_eyebrow_lower_right_quarter": {
          "x": 103,
          "y": 205
        },
        "left_eyebrow_right_corner": {
          "x": 120,
          "y": 199
        },
        "left_eyebrow_upper_left_quarter": {
          "x": 66,
          "y": 204
        },
        "left_eyebrow_upper_middle": {
          "x": 82,
          "y": 194
        },
        "left_eyebrow_upper_right_quarter": {
          "x": 102,
          "y": 191
        },
        "mouth_left_corner": {
          "x": 107,
          "y": 324
        },
        "mouth_lower_lip_bottom": {
          "x": 159,
          "y": 342
        },
        "mouth_lower_lip_left_contour1": {
          "x": 133,
          "y": 329
        },
        "mouth_lower_lip_left_contour2": {
          "x": 122,
          "y": 334
        },
        "mouth_lower_lip_left_contour3": {
          "x": 139,
          "y": 340
        },
        "mouth_lower_lip_right_contour1": {
          "x": 181,
          "y": 325
        },
        "mouth_lower_lip_right_contour2": {
          "x": 192,
          "y": 328
        },
        "mouth_lower_lip_right_contour3": {
          "x": 178,
          "y": 337
        },
        "mouth_lower_lip_top": {
          "x": 158,
          "y": 330
        },
        "mouth_right_corner": {
          "x": 202,
          "y": 315
        },
        "mouth_upper_lip_bottom": {
          "x": 157,
          "y": 323
        },
        "mouth_upper_lip_left_contour1": {
          "x": 146,
          "y": 315
        },
        "mouth_upper_lip_left_contour2": {
          "x": 127,
          "y": 319
        },
        "mouth_upper_lip_left_contour3": {
          "x": 133,
          "y": 323
        },
        "mouth_upper_lip_right_contour1": {
          "x": 167,
          "y": 314
        },
        "mouth_upper_lip_right_contour2": {
          "x": 185,
          "y": 314
        },
        "mouth_upper_lip_right_contour3": {
          "x": 180,
          "y": 319
        },
        "mouth_upper_lip_top": {
          "x": 157,
          "y": 317
        },
        "nose_contour_left1": {
          "x": 130,
          "y": 222
        },
        "nose_contour_left2": {
          "x": 125,
          "y": 260
        },
        "nose_contour_left3": {
          "x": 132,
          "y": 287
        },
        "nose_contour_lower_middle": {
          "x": 151,
          "y": 292
        },
        "nose_contour_right1": {
          "x": 160,
          "y": 218
        },
        "nose_contour_right2": {
          "x": 173,
          "y": 255
        },
        "nose_contour_right3": {
          "x": 170,
          "y": 283
        },
        "nose_left": {
          "x": 117,
          "y": 278
        },
        "nose_right": {
          "x": 185,
          "y": 271
        },
        "nose_tip": {
          "x": 149,
          "y": 277
        },
        "right_eye_bottom": {
          "x": 190,
          "y": 218
        },
        "right_eye_center": {
          "x": 189,
          "y": 214
        },
        "right_eye_left_corner": {
          "x": 170,
          "y": 218
        },
        "right_eye_lower_left_quarter": {
          "x": 180,
          "y": 218
        },
        "right_eye_lower_right_quarter": {
          "x": 199,
          "y": 217
        },
        "right_eye_pupil": {
          "x": 190,
          "y": 212
        },
        "right_eye_right_corner": {
          "x": 208,
          "y": 214
        },
        "right_eye_top": {
          "x": 188,
          "y": 207
        },
        "right_eye_upper_left_quarter": {
          "x": 178,
          "y": 210
        },
        "right_eye_upper_right_quarter": {
          "x": 199,
          "y": 209
        },
        "right_eyebrow_left_corner": {
          "x": 162,
          "y": 193
        },
        "right_eyebrow_lower_left_quarter": {
          "x": 180,
          "y": 196
        },
        "right_eyebrow_lower_middle": {
          "x": 198,
          "y": 197
        },
        "right_eyebrow_lower_right_quarter": {
          "x": 215,
          "y": 199
        },
        "right_eyebrow_right_corner": {
          "x": 232,
          "y": 203
        },
        "right_eyebrow_upper_left_quarter": {
          "x": 179,
          "y": 183
        },
        "right_eyebrow_upper_middle": {
          "x": 200,
          "y": 182
        },
        "right_eyebrow_upper_right_quarter": {
          "x": 219,
          "y": 188
        }
      },
      "attributes": {
        "gender": {
          "value": "Male"
        },
        "age": {
          "value": 64
        },
        "smile": {
          "value": 100,
          "threshold": 50
        },
        "headpose": {
          "pitch_angle": 2.6933928,
          "roll_angle": -6.67929,
          "yaw_angle": -0.68304366
        },
        "blur": {
          "blurness": {
            "value": 1.01,
            "threshold": 50
          },
          "motionblur": {
            "value": 1.01,
            "threshold": 50
          },
          "gaussianblur": {
            "value": 1.01,
            "threshold": 50
          }
        },
        "eyestatus": {
          "left_eye_status": {
            "no_glass_eye_open": 99.998,
            "no_glass_eye_close": 0,
            "normal_glass_eye_open": 0.002,
            "normal_glass_eye_close": 0,
            "dark_glasses": 0,
            "occlusion": 0.001
          },
          "right_eye_status": {
            "no_glass_eye_open": 99.973,
            "no_glass_eye_close": 0,
            "normal_glass_eye_open": 0.027,
            "normal_glass_eye_close": 0,
            "dark_glasses": 0,
            "occlusion": 0
          }
        },
        "facequality": {
          "value": 94.024,
          "threshold": 70.1
        },
        "glass": {
          "value": "None"
        }
      }
    }
  ],
  "image_id": "IsrKeGlZOocd9TyWKSRYkQ==",
  "face_num": 1
}
